{
"autoplayBgm":false,"autoplayBgs":false,"battleback1Name":"","battleback2Name":"","bgm":{"name":"","pan":0,"pitch":100,"volume":90},"bgs":{"name":"","pan":0,"pitch":100,"volume":90},"disableDashing":false,"displayName":"","encounterList":[],"encounterStep":30,"height":10,"note":"","parallaxLoopX":false,"parallaxLoopY":false,"parallaxName":"","parallaxShow":true,"parallaxSx":0,"parallaxSy":0,"scrollType":0,"specifyBattleback":false,"tilesetId":6,"width":10,
"data":[1536,1536,5904,5912,3264,3272,5920,1536,1536,1536,1536,5923,5917,5926,3264,3272,5929,5921,5925,1536,1536,5920,6274,6278,3264,3272,6275,6274,5920,1536,1536,5920,6280,6284,3264,3272,6281,6280,5920,1536,1536,5920,3282,3268,3249,3250,3268,3284,5920,1536,1536,5920,3264,3248,3248,3248,3248,3272,5920,1536,1536,5920,3264,3248,3248,3248,3248,3272,5920,1536,1536,5920,3288,3276,3276,3276,3276,3286,5920,1536,1536,5929,5921,5921,5921,5921,5921,5921,5927,1536,1536,1536,1536,1536,1536,1536,1536,1536,1536,1536,0,0,0,0,0,3148,0,0,0,0,0,0,0,0,0,0,0,0,0,0,0,0,0,0,0,0,0,3438,0,0,0,0,0,0,0,0,0,0,0,0,0,0,0,0,0,0,0,0,0,0,0,0,0,0,0,0,0,0,0,0,0,0,0,0,3150,0,0,0,0,0,0,0,0,0,0,0,0,0,0,0,0,0,0,0,0,0,0,0,0,0,0,0,0,0,0,0,0,0,0,0,0,0,0,0,0,0,0,0,0,0,0,0,0,0,0,0,0,0,0,0,0,0,416,0,0,0,0,0,0,0,0,0,109,0,0,0,0,0,0,0,0,0,0,0,0,0,0,0,0,0,0,0,0,0,0,0,0,0,0,0,0,0,0,0,0,0,0,0,0,0,0,0,0,0,0,0,0,0,0,0,0,0,0,0,0,0,0,0,0,0,0,0,0,0,0,0,0,0,0,0,0,0,0,0,120,120,0,0,0,0,0,0,0,0,0,0,0,0,0,0,0,0,163,0,0,0,0,117,0,0,0,0,171,287,0,0,0,0,0,0,0,0,0,0,0,0,0,108,0,0,0,0,0,0,0,0,0,0,0,0,0,0,225,0,0,0,0,0,0,0,0,0,233,0,0,0,0,0,0,0,0,0,0,0,0,0,0,0,0,0,0,0,0,0,0,0,0,0,0,0,0,0,0,0,0,0,0,0,0,0,0,0,0,0,5,0,0,0,0,0,0,0,0,0,5,0,0,0,0,5,0,0,0,0,5,0,0,0,0,5,0,0,5,0,0,0,0,0,0,5,0,0,5,0,0,0,0,0,0,5,0,0,5,0,0,0,0,0,0,5,0,0,5,0,0,0,0,0,0,5,0,0,0,0,0,0,0,0,0,5,0,0,0,0,0,0,0,0,0,0,0,0,0,0,0,0,0,0,0,0,0,0,0,0,0,0,0,0,0,0,0,0,0,0,0,0,0,0,0,0,0,0,0,0,0,0,0,0,0,0,0,0,0,0,0,0,0,0,0,0,0,0,0,0,0,0,0,0,0,0,0,0,0,0,0,0,0,0,0,0,0,0,0,0,0,0,0,0,0,0,0,0,0,0,0,0,0,0,0,0,0,0,0,0,0,0,0,0,0,0],
"events":[
null,
{"id":1,"name":"EV001","note":"","pages":[{"conditions":{"actorId":1,"actorValid":false,"itemId":1,"itemValid":false,"selfSwitchCh":"A","selfSwitchValid":false,"switch1Id":1,"switch1Valid":false,"switch2Id":1,"switch2Valid":false,"variableId":1,"variableValid":false,"variableValue":0},"directionFix":false,"image":{"characterIndex":0,"characterName":"","direction":2,"pattern":0,"tileId":0},"list":[{"code":201,"indent":0,"parameters":[0,14,21,29,0,0]},{"code":0,"indent":0,"parameters":[]}],"moveFrequency":3,"moveRoute":{"list":[{"code":0,"parameters":[]}],"repeat":true,"skippable":false,"wait":false},"moveSpeed":3,"moveType":0,"priorityType":0,"stepAnime":false,"through":false,"trigger":0,"walkAnime":true}],"x":4,"y":1},
{"id":2,"name":"EV002","note":"","pages":[{"conditions":{"actorId":1,"actorValid":false,"itemId":1,"itemValid":false,"selfSwitchCh":"A","selfSwitchValid":false,"switch1Id":1,"switch1Valid":false,"switch2Id":1,"switch2Valid":false,"variableId":1,"variableValid":false,"variableValue":0},"directionFix":false,"image":{"characterIndex":0,"characterName":"","direction":2,"pattern":0,"tileId":0},"list":[{"code":201,"indent":0,"parameters":[0,14,22,29,0,0]},{"code":0,"indent":0,"parameters":[]}],"moveFrequency":3,"moveRoute":{"list":[{"code":0,"parameters":[]}],"repeat":true,"skippable":false,"wait":false},"moveSpeed":3,"moveType":0,"priorityType":0,"stepAnime":false,"through":false,"trigger":0,"walkAnime":true}],"x":5,"y":1},
{"id":3,"name":"EV003","note":"","pages":[{"conditions":{"actorId":1,"actorValid":false,"itemId":1,"itemValid":false,"selfSwitchCh":"A","selfSwitchValid":false,"switch1Id":19,"switch1Valid":false,"switch2Id":1,"switch2Valid":false,"variableId":1,"variableValid":false,"variableValue":0},"directionFix":false,"image":{"tileId":0,"characterName":"梦境幼年行走图","direction":2,"pattern":0,"characterIndex":0},"list":[{"code":205,"indent":0,"parameters":[-1,{"list":[{"code":25,"indent":null},{"code":0}],"repeat":false,"skippable":false,"wait":false}]},{"code":505,"indent":0,"parameters":[{"code":25,"indent":null}]},{"code":101,"indent":0,"parameters":["梦境脸图",4,0,2]},{"code":401,"indent":0,"parameters":["【1562】"]},{"code":401,"indent":0,"parameters":["！！！"]},{"code":101,"indent":0,"parameters":["梦境脸图",4,0,2]},{"code":401,"indent":0,"parameters":["【1562】"]},{"code":401,"indent":0,"parameters":["你……"]},{"code":101,"indent":0,"parameters":["梦境脸图",3,0,2]},{"code":401,"indent":0,"parameters":["【】"]},{"code":401,"indent":0,"parameters":["你好啊！"]},{"code":101,"indent":0,"parameters":["梦境脸图",3,0,2]},{"code":401,"indent":0,"parameters":["【】"]},{"code":401,"indent":0,"parameters":["你是1562吗？"]},{"code":101,"indent":0,"parameters":["",0,0,2]},{"code":401,"indent":0,"parameters":["面前的孩子没有回答我，只是低头看了看自己身上别着的名牌。"]},{"code":101,"indent":0,"parameters":["梦境脸图",4,0,2]},{"code":401,"indent":0,"parameters":["【1562】"]},{"code":401,"indent":0,"parameters":["现在是3684……"]},{"code":101,"indent":0,"parameters":["",0,0,2]},{"code":401,"indent":0,"parameters":["是他，救了我的“英雄”。"]},{"code":101,"indent":0,"parameters":["",0,0,2]},{"code":401,"indent":0,"parameters":["看着他身上的伤，我一时有些心酸。"]},{"code":101,"indent":0,"parameters":["",0,0,2]},{"code":401,"indent":0,"parameters":["总觉得他不该这样。"]},{"code":101,"indent":0,"parameters":["",0,0,2]},{"code":401,"indent":0,"parameters":["他应该站在最高的地方，散发着独属于他的光芒。"]},{"code":101,"indent":0,"parameters":["",0,0,2]},{"code":401,"indent":0,"parameters":["他应该被热爱着，被温柔以待。"]},{"code":101,"indent":0,"parameters":["",0,0,2]},{"code":401,"indent":0,"parameters":["而且不是沉默的，被困于如此狭隘的地方。"]},{"code":101,"indent":0,"parameters":["梦境脸图",3,0,2]},{"code":401,"indent":0,"parameters":["【】"]},{"code":401,"indent":0,"parameters":["所以，你是1562吗？"]},{"code":101,"indent":0,"parameters":["梦境脸图",6,0,2]},{"code":401,"indent":0,"parameters":["【1562】"]},{"code":401,"indent":0,"parameters":["是……"]},{"code":101,"indent":0,"parameters":["梦境脸图",3,0,2]},{"code":401,"indent":0,"parameters":["【】"]},{"code":401,"indent":0,"parameters":["那就对了，我没找错！"]},{"code":101,"indent":0,"parameters":["梦境脸图",3,0,2]},{"code":401,"indent":0,"parameters":["【】"]},{"code":401,"indent":0,"parameters":["我捡到了这个，是你的吗？"]},{"code":126,"indent":0,"parameters":[7,1,0,1]},{"code":101,"indent":0,"parameters":["",0,0,2]},{"code":401,"indent":0,"parameters":["失去道具『破烂的小熊』"]},{"code":101,"indent":0,"parameters":["梦境脸图",5,0,2]},{"code":401,"indent":0,"parameters":["【1562】"]},{"code":401,"indent":0,"parameters":["！"]},{"code":101,"indent":0,"parameters":["梦境脸图",5,0,2]},{"code":401,"indent":0,"parameters":["【1562】"]},{"code":401,"indent":0,"parameters":["熊"]},{"code":101,"indent":0,"parameters":["",0,0,2]},{"code":401,"indent":0,"parameters":["他接过小熊，视作珍宝的把它抱进怀里。"]},{"code":101,"indent":0,"parameters":["",0,0,2]},{"code":401,"indent":0,"parameters":["眼神十分的温柔，仿佛装入了星星。"]},{"code":101,"indent":0,"parameters":["",0,0,2]},{"code":401,"indent":0,"parameters":["……有点酸这只熊了。"]},{"code":101,"indent":0,"parameters":["",0,0,2]},{"code":401,"indent":0,"parameters":["看着珍惜的看着小熊的他，我忍不住开了口。"]},{"code":101,"indent":0,"parameters":["梦境脸图",3,0,2]},{"code":401,"indent":0,"parameters":["【】"]},{"code":401,"indent":0,"parameters":["那么，1562。"]},{"code":101,"indent":0,"parameters":["梦境脸图",3,0,2]},{"code":401,"indent":0,"parameters":["【】"]},{"code":401,"indent":0,"parameters":["你愿意跟我一起走吗？"]},{"code":101,"indent":0,"parameters":["梦境脸图",4,0,2]},{"code":401,"indent":0,"parameters":["【1562】"]},{"code":401,"indent":0,"parameters":["走？"]},{"code":101,"indent":0,"parameters":["梦境脸图",3,0,2]},{"code":401,"indent":0,"parameters":["【】"]},{"code":401,"indent":0,"parameters":["对啊，我们一起出去。"]},{"code":101,"indent":0,"parameters":["梦境脸图",3,0,2]},{"code":401,"indent":0,"parameters":["【】"]},{"code":401,"indent":0,"parameters":["之前答应你的糖果，我可以带你去找。"]},{"code":101,"indent":0,"parameters":["梦境脸图",3,0,2]},{"code":401,"indent":0,"parameters":["【】"]},{"code":401,"indent":0,"parameters":["还有之前说的好玩的，等出去后……"]},{"code":101,"indent":0,"parameters":["梦境脸图",3,0,2]},{"code":401,"indent":0,"parameters":["【】"]},{"code":401,"indent":0,"parameters":["我们可以……"]},{"code":101,"indent":0,"parameters":["梦境脸图",6,0,2]},{"code":401,"indent":0,"parameters":["【1562】"]},{"code":401,"indent":0,"parameters":["好。"]},{"code":101,"indent":0,"parameters":["",0,0,2]},{"code":401,"indent":0,"parameters":["啊，答应的真干脆。"]},{"code":101,"indent":0,"parameters":["",0,0,2]},{"code":401,"indent":0,"parameters":["我还准备了一肚子话呢……"]},{"code":101,"indent":0,"parameters":["",0,0,2]},{"code":401,"indent":0,"parameters":["不过答应就好，这一次，我们一定要一起呀。"]},{"code":101,"indent":0,"parameters":["",0,0,2]},{"code":401,"indent":0,"parameters":["[1562加入了队伍]"]},{"code":129,"indent":0,"parameters":[3,0,false]},{"code":121,"indent":0,"parameters":[21,21,0]},{"code":121,"indent":0,"parameters":[16,16,0]},{"code":121,"indent":0,"parameters":[19,19,1]},{"code":123,"indent":0,"parameters":["A",0]},{"code":0,"indent":0,"parameters":[]}],"moveFrequency":3,"moveRoute":{"list":[{"code":0,"parameters":[]}],"repeat":true,"skippable":false,"wait":false},"moveSpeed":3,"moveType":0,"priorityType":1,"stepAnime":false,"through":false,"trigger":0,"walkAnime":true},{"conditions":{"actorId":1,"actorValid":false,"itemId":1,"itemValid":false,"selfSwitchCh":"A","selfSwitchValid":true,"switch1Id":1,"switch1Valid":false,"switch2Id":1,"switch2Valid":false,"variableId":1,"variableValid":false,"variableValue":0},"directionFix":false,"image":{"characterIndex":0,"characterName":"","direction":2,"pattern":0,"tileId":0},"list":[{"code":0,"indent":0,"parameters":[]}],"moveFrequency":3,"moveRoute":{"list":[{"code":0,"parameters":[]}],"repeat":true,"skippable":false,"wait":false},"moveSpeed":3,"moveType":0,"priorityType":0,"stepAnime":false,"through":false,"trigger":0,"walkAnime":true}],"x":4,"y":5}
]
}